docs/conf.py
edexplore/__init__.py
edexplore/defined.py
edexplore/main.py
edexplore/constants/__init__.py
edexplore/constants/constants.py
edexplore/helpers/__init__.py
edexplore/helpers/helpers.py
edexplore-1.0.1.dist-info/LICENSE
edexplore-1.0.1.dist-info/METADATA
edexplore-1.0.1.dist-info/WHEEL
edexplore-1.0.1.dist-info/top_level.txt
edexplore-1.0.1.dist-info/RECORD
