Metadata-Version: 2.1
Name: edexplore
Version: 1.0.1
Summary: A simple widget for interactive EDA / QA for those who use Pandas in Jupyter Notebook.
Home-page: https://github.com/nagaprakashv/edexplore/
Author: nagaprakash venkatesan
Author-email: npv3105@outlook.com
License-File: LICENSE
Requires-Dist: numpy >=1.25.2
Requires-Dist: pandas >=2.0.3
Requires-Dist: ipywidgets >=8.1.0
Requires-Dist: notebook >=7.0.2
